<?xml version="1.0" encoding="utf-16"?><Profession xmlns:xsi="http://www.w3.org/2001/XMLSchema-instance" xmlns:xsd="http://www.w3.org/2001/XMLSchema"><ProfessionName>Bezopasnost</ProfessionName><ListOfInfoAboutOffers><SalaryInfo><Salary>500</Salary></SalaryInfo><SalaryInfo><Salary>500</Salary></SalaryInfo><SalaryInfo><Salary>700</Salary></SalaryInfo><SalaryInfo><Salary>912</Salary></SalaryInfo><SalaryInfo><Salary>615</Salary></SalaryInfo><SalaryInfo><Salary>600</Salary></SalaryInfo><SalaryInfo><Salary>650</Salary></SalaryInfo><SalaryInfo><Salary>450</Salary></SalaryInfo><SalaryInfo><Salary>600</Salary></SalaryInfo><SalaryInfo><Salary>450</Salary></SalaryInfo><SalaryInfo><Salary>450</Salary></SalaryInfo><SalaryInfo><Salary>700</Salary></SalaryInfo><SalaryInfo><Salary>1000</Salary></SalaryInfo><SalaryInfo><Salary>300</Salary></SalaryInfo><SalaryInfo><Salary>450</Salary></SalaryInfo><SalaryInfo><Salary>300</Salary></SalaryInfo><SalaryInfo><Salary>750</Salary></SalaryInfo><SalaryInfo><Salary>500</Salary></SalaryInfo><SalaryInfo><Salary>750</Salary></SalaryInfo><SalaryInfo><Salary>210</Salary></SalaryInfo><SalaryInfo><Salary>500</Salary></SalaryInfo><SalaryInfo><Salary>450</Salary></SalaryInfo><SalaryInfo><Salary>690</Salary></SalaryInfo><SalaryInfo><Salary>620</Salary></SalaryInfo><SalaryInfo><Salary>700</Salary></SalaryInfo><SalaryInfo><Salary>690</Salary></SalaryInfo><SalaryInfo><Salary>500</Salary></SalaryInfo><SalaryInfo><Salary>420</Salary></SalaryInfo><SalaryInfo><Salary>1200</Salary></SalaryInfo><SalaryInfo><Salary>400</Salary></SalaryInfo><SalaryInfo><Salary>500</Salary></SalaryInfo><SalaryInfo><Salary>1200</Salary></SalaryInfo><SalaryInfo><Salary>700</Salary></SalaryInfo><SalaryInfo><Salary>200</Salary></SalaryInfo><SalaryInfo><Salary>900</Salary></SalaryInfo><SalaryInfo><Salary>700</Salary></SalaryInfo><SalaryInfo><Salary>800</Salary></SalaryInfo><SalaryInfo><Salary>500</Salary></SalaryInfo><SalaryInfo><Salary>500</Salary></SalaryInfo><SalaryInfo><Salary>800</Salary></SalaryInfo><SalaryInfo><Salary>800</Salary></SalaryInfo><SalaryInfo><Salary>800</Salary></SalaryInfo><SalaryInfo><Salary>250</Salary></SalaryInfo><SalaryInfo><Salary>500</Salary></SalaryInfo><SalaryInfo><Salary>600</Salary></SalaryInfo><SalaryInfo><Salary>400</Salary></SalaryInfo><SalaryInfo><Salary>500</Salary></SalaryInfo><SalaryInfo><Salary>300</Salary></SalaryInfo><SalaryInfo><Salary>330</Salary></SalaryInfo><SalaryInfo><Salary>550</Salary></SalaryInfo><SalaryInfo><Salary>450</Salary></SalaryInfo><SalaryInfo><Salary>400</Salary></SalaryInfo><SalaryInfo><Salary>200</Salary></SalaryInfo><SalaryInfo><Salary>500</Salary></SalaryInfo><SalaryInfo><Salary>700</Salary></SalaryInfo><SalaryInfo><Salary>300</Salary></SalaryInfo><SalaryInfo><Salary>500</Salary></SalaryInfo><SalaryInfo><Salary>1000</Salary></SalaryInfo><SalaryInfo><Salary>600</Salary></SalaryInfo><SalaryInfo><Salary>400</Salary></SalaryInfo><SalaryInfo><Salary>550</Salary></SalaryInfo><SalaryInfo><Salary>1000</Salary></SalaryInfo><SalaryInfo><Salary>500</Salary></SalaryInfo><SalaryInfo><Salary>500</Salary></SalaryInfo><SalaryInfo><Salary>300</Salary></SalaryInfo><SalaryInfo><Salary>200</Salary></SalaryInfo><SalaryInfo><Salary>600</Salary></SalaryInfo><SalaryInfo><Salary>600</Salary></SalaryInfo><SalaryInfo><Salary>400</Salary></SalaryInfo><SalaryInfo><Salary>500</Salary></SalaryInfo><SalaryInfo><Salary>450</Salary></SalaryInfo><SalaryInfo><Salary>500</Salary></SalaryInfo></ListOfInfoAboutOffers></Profession>